rosmodex/__init__.py
rosmodex/__main__.py
rosmodex/cli.py
ros_modex-0.0.0.dist-info/LICENSE
ros_modex-0.0.0.dist-info/METADATA
ros_modex-0.0.0.dist-info/WHEEL
ros_modex-0.0.0.dist-info/entry_points.txt
ros_modex-0.0.0.dist-info/top_level.txt
ros_modex-0.0.0.dist-info/RECORD
