Metadata-Version: 2.1
Name: ros-modex
Version: 0.0.0
Summary: A model extraction and analysis tool for ROS systems
Home-page: https://github.com/git-afsantos/ros-modex
Author: André Santos
Author-email: haros.framework@gmail.com
License: MIT
Project-URL: Source, https://github.com/git-afsantos/ros-modex/
Project-URL: Tracker, https://github.com/git-afsantos/ros-modex/issues
Keywords: ros,variability,model extraction,feature models
Platform: UNKNOWN
Classifier: Development Status :: 3 - Alpha
Classifier: Intended Audience :: Developers
Classifier: Intended Audience :: Science/Research
Classifier: License :: OSI Approved :: MIT License
Classifier: Operating System :: POSIX :: Linux
Classifier: Programming Language :: Python :: 3
Classifier: Programming Language :: Python :: 3.8
Classifier: Programming Language :: Python :: 3.9
Classifier: Programming Language :: Python :: 3.10
Classifier: Programming Language :: Python :: 3 :: Only
Classifier: Topic :: Scientific/Engineering
Classifier: Topic :: Software Development
Classifier: Topic :: Software Development :: Libraries
Classifier: Topic :: Software Development :: Quality Assurance
Requires-Python: >=3.8, <4
License-File: LICENSE
Provides-Extra: dev
Requires-Dist: pytest ; extra == 'dev'
Requires-Dist: tox ; extra == 'dev'
